{"5700": {"frame": 5700, "objects": [{"track_id": 21, "bbox": [353.4769287109375, 41.59739685058594, 372.470458984375, 63.69146728515625], "class_id": 0, "class_name": "player", "team_id": -1}, {"track_id": 0, "bbox": [4.006582260131836, 165.58053588867188, 18.613115310668945, 176.20181274414062], "class_id": 1, "class_name": "ball", "team_id": -1}], "ball_owner": -1, "possession_team": -1, "spatial_info": {"field_position": [52.5, 29.29331837052479], "zone_id": 2, "zone_name": "def_right", "calibration_valid": true, "position_fallback": false}}, "5701": {"frame": 5701, "objects": [{"track_id": 23, "bbox": [352.98114013671875, 41.24110412597656, 372.73834228515625, 63.58454895019531], "class_id": 0, "class_name": "player", "team_id": -1}, {"track_id": 0, "bbox": [3.9489479064941406, 165.43800354003906, 19.82774543762207, 176.72666931152344], "class_id": 1, "class_name": "ball", "team_id": -1}], "ball_owner": -1, "possession_team": -1, "spatial_info": {"field_position": [52.49999999999999, 29.287200892500675], "zone_id": 2, "zone_name": "def_right", "calibration_valid": true, "position_fallback": false}}, "5702": {"frame": 5702, "objects": [{"track_id": 2, "bbox": [353.06719970703125, 39.507408142089844, 373.29949951171875, 63.78472900390625], "class_id": 0, "class_name": "player", "team_id": -1}, {"track_id": 0, "bbox": [3.9775619506835938, 165.2964324951172, 20.942508697509766, 177.05018615722656], "class_id": 1, "class_name": "ball", "team_id": -1}], "ball_owner": -1, "possession_team": -1, "spatial_info": {"field_position": [52.5, 29.294989187052753], "zone_id": 2, "zone_name": "def_right", "calibration_valid": true, "position_fallback": false}}, "5703": {"frame": 5703, "objects": [{"track_id": 8, "bbox": [353.00701904296875, 38.97759246826172, 373.43048095703125, 64.06702423095703], "class_id": 0, "class_name": "player", "team_id": -1}, {"track_id": 0, "bbox": [4.756380081176758, 165.68353271484375, 20.35293197631836, 176.615966796875], "class_id": 1, "class_name": "ball", "team_id": -1}], "ball_owner": -1, "possession_team": -1, "spatial_info": {"field_position": [52.5, 29.331106701374445], "zone_id": 2, "zone_name": "def_right", "calibration_valid": true, "position_fallback": false}}, "5704": {"frame": 5704, "objects": [{"track_id": 17, "bbox": [353.1181640625, 35.21674346923828, 374.37744140625, 64.80560302734375], "class_id": 0, "class_name": "player", "team_id": -1}, {"track_id": 0, "bbox": [5.217746734619141, 165.74151611328125, 21.11142349243164, 177.04803466796875], "class_id": 1, "class_name": "ball", "team_id": -1}], "ball_owner": -1, "possession_team": -1, "spatial_info": {"field_position": [52.5, 29.33355661181094], "zone_id": 2, "zone_name": "def_right", "calibration_valid": true, "position_fallback": false}}, "5705": {"frame": 5705, "objects": [{"track_id": 10, "bbox": [237.08859252929688, 153.260986328125, 249.48971557617188, 182.83428955078125], "class_id": 0, "class_name": "player", "team_id": -1}, {"track_id": 0, "bbox": [5.806074142456055, 165.76255798339844, 20.00735855102539, 176.23915100097656], "class_id": 1, "class_name": "ball", "team_id": -1}], "ball_owner": -1, "possession_team": -1, "spatial_info": {"field_position": [52.5, 29.37740190001514], "zone_id": 2, "zone_name": "def_right", "calibration_valid": true, "position_fallback": false}}, "5706": {"frame": 5706, "objects": [{"track_id": 13, "bbox": [353.1082763671875, 35.66179656982422, 374.355712890625, 64.80838012695312], "class_id": 0, "class_name": "player", "team_id": -1}, {"track_id": 0, "bbox": [5.1197967529296875, 165.22573852539062, 21.509658813476562, 177.22808837890625], "class_id": 1, "class_name": "ball", "team_id": -1}], "ball_owner": -1, "possession_team": -1, "spatial_info": {"field_position": [52.5, 29.328856913448174], "zone_id": 2, "zone_name": "def_right", "calibration_valid": true, "position_fallback": false}}, "5707": {"frame": 5707, "objects": [{"track_id": 12, "bbox": [236.91946411132812, 152.55348205566406, 248.45803833007812, 182.1967315673828], "class_id": 0, "class_name": "player", "team_id": -1}, {"track_id": 0, "bbox": [5.155918121337891, 165.25344848632812, 21.540714263916016, 177.23403930664062], "class_id": 1, "class_name": "ball", "team_id": -1}], "ball_owner": -1, "possession_team": -1, "spatial_info": {"field_position": [52.5, 29.330276977885475], "zone_id": 2, "zone_name": "def_right", "calibration_valid": true, "position_fallback": false}}, "5708": {"frame": 5708, "objects": [{"track_id": 12, "bbox": [236.77529907226562, 152.1890869140625, 248.70095825195312, 181.8717041015625], "class_id": 0, "class_name": "player", "team_id": -1}, {"track_id": 0, "bbox": [4.8289794921875, 165.14337158203125, 21.16842269897461, 177.33056640625], "class_id": 1, "class_name": "ball", "team_id": -1}], "ball_owner": -1, "possession_team": -1, "spatial_info": {"field_position": [52.49999999999999, 29.30417930334283], "zone_id": 2, "zone_name": "def_right", "calibration_valid": true, "position_fallback": false}}, "5709": {"frame": 5709, "objects": [{"track_id": 12, "bbox": [236.4136962890625, 153.231201171875, 248.65081787109375, 181.52972412109375], "class_id": 0, "class_name": "player", "team_id": -1}, {"track_id": 0, "bbox": [4.796100616455078, 165.1892547607422, 21.210567474365234, 177.25929260253906], "class_id": 1, "class_name": "ball", "team_id": -1}], "ball_owner": -1, "possession_team": -1, "spatial_info": {"field_position": [52.5, 29.309546995843554], "zone_id": 2, "zone_name": "def_right", "calibration_valid": true, "position_fallback": false}}, "5710": {"frame": 5710, "objects": [{"track_id": 15, "bbox": [353.70306396484375, 46.96223831176758, 370.02191162109375, 65.08747863769531], "class_id": 0, "class_name": "player", "team_id": -1}, {"track_id": 12, "bbox": [235.9593963623047, 155.5276641845703, 247.93260192871094, 182.0446014404297], "class_id": 0, "class_name": "player", "team_id": -1}, {"track_id": 11, "bbox": [128.2310791015625, 19.579086303710938, 145.00042724609375, 34.251304626464844], "class_id": 0, "class_name": "player", "team_id": 1}, {"track_id": 0, "bbox": [6.288259506225586, 166.14828491210938, 20.52313804626465, 176.12643432617188], "class_id": 1, "class_name": "ball", "team_id": -1}], "ball_owner": -1, "possession_team": -1, "spatial_info": {"field_position": [52.5, 29.413301884683136], "zone_id": 2, "zone_name": "def_right", "calibration_valid": true, "position_fallback": false}}, "5711": {"frame": 5711, "objects": [{"track_id": 15, "bbox": [353.8414306640625, 47.00846862792969, 369.91729736328125, 65.00227355957031], "class_id": 0, "class_name": "player", "team_id": -1}, {"track_id": 12, "bbox": [235.74508666992188, 155.2054443359375, 247.6937255859375, 182.1070556640625], "class_id": 0, "class_name": "player", "team_id": -1}, {"track_id": 11, "bbox": [128.30538940429688, 19.378328323364258, 144.86953735351562, 33.911590576171875], "class_id": 0, "class_name": "player", "team_id": 1}, {"track_id": 0, "bbox": [6.489842891693115, 166.2204132080078, 19.700647354125977, 176.00193786621094], "class_id": 1, "class_name": "ball", "team_id": -1}], "ball_owner": -1, "possession_team": -1, "spatial_info": {"field_position": [52.5, 29.40489650557513], "zone_id": 2, "zone_name": "def_right", "calibration_valid": true, "position_fallback": false}}, "5712": {"frame": 5712, "objects": [{"track_id": 15, "bbox": [353.9200744628906, 46.992557525634766, 370.0747375488281, 65.12161254882812], "class_id": 0, "class_name": "player", "team_id": -1}, {"track_id": 12, "bbox": [235.75221252441406, 155.65866088867188, 247.1725616455078, 181.93136596679688], "class_id": 0, "class_name": "player", "team_id": -1}, {"track_id": 11, "bbox": [128.12985229492188, 19.175975799560547, 143.88299560546875, 33.775028228759766], "class_id": 0, "class_name": "player", "team_id": 1}, {"track_id": 0, "bbox": [7.632684707641602, 166.40695190429688, 19.129119873046875, 175.45498657226562], "class_id": 1, "class_name": "ball", "team_id": -1}], "ball_owner": -1, "possession_team": -1, "spatial_info": {"field_position": [52.49999999999999, 29.46030596569801], "zone_id": 2, "zone_name": "def_right", "calibration_valid": true, "position_fallback": false}}, "5713": {"frame": 5713, "objects": [{"track_id": 15, "bbox": [354.14410400390625, 47.101531982421875, 370.15228271484375, 65.09120178222656], "class_id": 0, "class_name": "player", "team_id": -1}, {"track_id": 3, "bbox": [235.36956787109375, 155.12718200683594, 247.0391845703125, 181.8970184326172], "class_id": 0, "class_name": "player", "team_id": -1}, {"track_id": 0, "bbox": [8.159082412719727, 166.25222778320312, 20.395566940307617, 175.20840454101562], "class_id": 1, "class_name": "ball", "team_id": -1}], "ball_owner": -1, "possession_team": -1, "spatial_info": {"field_position": [52.50000000000001, 29.529582602548274], "zone_id": -1, "zone_name": "unknown", "calibration_valid": true, "position_fallback": false}}, "5714": {"frame": 5714, "objects": [{"track_id": 16, "bbox": [354.011962890625, 47.21900939941406, 370.14697265625, 65.15107727050781], "class_id": 0, "class_name": "player", "team_id": -1}, {"track_id": 0, "bbox": [8.367916107177734, 166.12109375, 23.134109497070312, 175.73318481445312], "class_id": 1, "class_name": "ball", "team_id": -1}], "ball_owner": -1, "possession_team": -1, "spatial_info": {"field_position": [52.5, 29.57780314257271], "zone_id": 2, "zone_name": "def_right", "calibration_valid": true, "position_fallback": false}}, "5715": {"frame": 5715, "objects": [{"track_id": 4, "bbox": [353.90130615234375, 47.1636848449707, 370.31219482421875, 65.27879333496094], "class_id": 0, "class_name": "player", "team_id": -1}, {"track_id": 0, "bbox": [8.772783279418945, 165.98944091796875, 24.267187118530273, 176.102294921875], "class_id": 1, "class_name": "ball", "team_id": -1}], "ball_owner": -1, "possession_team": -1, "spatial_info": {"field_position": [52.5, 29.596532380464126], "zone_id": 2, "zone_name": "def_right", "calibration_valid": true, "position_fallback": false}}, "5716": {"frame": 5716, "objects": [{"track_id": 6, "bbox": [353.82293701171875, 47.17966842651367, 370.48651123046875, 64.62547302246094], "class_id": 0, "class_name": "player", "team_id": -1}, {"track_id": 19, "bbox": [234.43443298339844, 155.9601287841797, 246.9570770263672, 182.78919982910156], "class_id": 0, "class_name": "player", "team_id": -1}, {"track_id": 0, "bbox": [9.005958557128906, 165.970947265625, 23.99416732788086, 176.1240234375], "class_id": 1, "class_name": "ball", "team_id": -1}], "ball_owner": -1, "possession_team": -1, "spatial_info": {"field_position": [52.50000000000001, 29.593700347369793], "zone_id": -1, "zone_name": "unknown", "calibration_valid": true, "position_fallback": false}}, "5717": {"frame": 5717, "objects": [{"track_id": 22, "bbox": [353.6502685546875, 46.93366241455078, 370.67962646484375, 64.96907806396484], "class_id": 0, "class_name": "player", "team_id": -1}, {"track_id": 0, "bbox": [8.937300682067871, 165.9195556640625, 23.929000854492188, 176.31982421875], "class_id": 1, "class_name": "ball", "team_id": -1}], "ball_owner": -1, "possession_team": -1, "spatial_info": {"field_position": [52.5, 29.5750123724879], "zone_id": 2, "zone_name": "def_right", "calibration_valid": true, "position_fallback": false}}, "5718": {"frame": 5718, "objects": [{"track_id": 18, "bbox": [234.44805908203125, 154.82571411132812, 246.6776123046875, 183.12008666992188], "class_id": 0, "class_name": "player", "team_id": -1}, {"track_id": 0, "bbox": [8.918802261352539, 165.78665161132812, 23.979299545288086, 176.4915771484375], "class_id": 1, "class_name": "ball", "team_id": -1}], "ball_owner": -1, "possession_team": -1, "spatial_info": {"field_position": [52.49999999999999, 29.56312083878276], "zone_id": 2, "zone_name": "def_right", "calibration_valid": true, "position_fallback": false}}, "5719": {"frame": 5719, "objects": [{"track_id": 9, "bbox": [234.0413360595703, 154.85589599609375, 246.40553283691406, 183.42910766601562], "class_id": 0, "class_name": "player", "team_id": 0}, {"track_id": 0, "bbox": [407.29046630859375, 164.0395050048828, 413.20782470703125, 170.87770080566406], "class_id": 1, "class_name": "ball", "team_id": -1}], "ball_owner": -1, "possession_team": -1, "spatial_info": {"field_position": [52.49999999999999, 23.360751222397663], "zone_id": 2, "zone_name": "def_right", "calibration_valid": true, "position_fallback": false}}, "5720": {"frame": 5720, "objects": [{"track_id": 9, "bbox": [234.15484619140625, 154.70968627929688, 246.266845703125, 183.50192260742188], "class_id": 0, "class_name": "player", "team_id": 0}, {"track_id": 0, "bbox": [407.11895751953125, 164.00177001953125, 413.31976318359375, 171.07049560546875], "class_id": 1, "class_name": "ball", "team_id": -1}], "ball_owner": -1, "possession_team": -1, "spatial_info": {"field_position": [52.49999999999999, 23.36435926959154], "zone_id": 2, "zone_name": "def_right", "calibration_valid": true, "position_fallback": false}}, "5721": {"frame": 5721, "objects": [{"track_id": 9, "bbox": [233.99810791015625, 154.77362060546875, 246.220947265625, 183.42483520507812], "class_id": 0, "class_name": "player", "team_id": 0}, {"track_id": 6, "bbox": [353.39520263671875, 47.128028869628906, 371.30706787109375, 68.29363250732422], "class_id": 0, "class_name": "player", "team_id": -1}, {"track_id": 0, "bbox": [9.597949981689453, 166.1072998046875, 22.554607391357422, 176.11093139648438], "class_id": 1, "class_name": "ball", "team_id": -1}], "ball_owner": -1, "possession_team": -1, "spatial_info": {"field_position": [52.5, 29.569179505765156], "zone_id": 2, "zone_name": "def_right", "calibration_valid": true, "position_fallback": false}}, "5722": {"frame": 5722, "objects": [{"track_id": 6, "bbox": [352.7581787109375, 47.09379577636719, 371.7947998046875, 68.69505310058594], "class_id": 0, "class_name": "player", "team_id": -1}, {"track_id": 9, "bbox": [233.93789672851562, 154.94053649902344, 245.79531860351562, 183.5012969970703], "class_id": 0, "class_name": "player", "team_id": 0}, {"track_id": 0, "bbox": [10.5062837600708, 165.99606323242188, 22.646114349365234, 176.14810180664062], "class_id": 1, "class_name": "ball", "team_id": -1}], "ball_owner": -1, "possession_team": -1, "spatial_info": {"field_position": [52.50000000000001, 29.59650518460097], "zone_id": -1, "zone_name": "unknown", "calibration_valid": true, "position_fallback": false}}, "5723": {"frame": 5723, "objects": [{"track_id": 6, "bbox": [353.662841796875, 47.399810791015625, 371.713134765625, 67.88345336914062], "class_id": 0, "class_name": "player", "team_id": -1}, {"track_id": 9, "bbox": [234.00894165039062, 155.0558319091797, 245.61056518554688, 183.13890075683594], "class_id": 0, "class_name": "player", "team_id": 0}, {"track_id": 21, "bbox": [270.5700378417969, 48.060523986816406, 281.7376403808594, 62.27582550048828], "class_id": 0, "class_name": "player", "team_id": -1}, {"track_id": 0, "bbox": [358.68927001953125, 242.23101806640625, 366.51507568359375, 250.154541015625], "class_id": 1, "class_name": "ball", "team_id": -1}], "ball_owner": -1, "possession_team": -1, "spatial_info": {"field_position": [52.49999999999999, 24.927010402653014], "zone_id": 2, "zone_name": "def_right", "calibration_valid": true, "position_fallback": false}}, "5724": {"frame": 5724, "objects": [{"track_id": 1, "bbox": [234.0323486328125, 155.3343505859375, 245.11944580078125, 182.90255737304688], "class_id": 0, "class_name": "player", "team_id": -1}, {"track_id": 0, "bbox": [358.9132385253906, 241.36691284179688, 367.3257751464844, 250.07461547851562], "class_id": 1, "class_name": "ball", "team_id": -1}], "ball_owner": -1, "possession_team": -1, "spatial_info": {"field_position": [52.49999999999999, 24.92478600628973], "zone_id": 2, "zone_name": "def_right", "calibration_valid": true, "position_fallback": false}}, "5725": {"frame": 5725, "objects": [{"track_id": 5, "bbox": [353.56488037109375, 46.975826263427734, 371.68035888671875, 68.28253173828125], "class_id": 0, "class_name": "player", "team_id": -1}, {"track_id": 14, "bbox": [233.4783477783203, 154.85305786132812, 245.8607635498047, 184.43240356445312], "class_id": 0, "class_name": "player", "team_id": -1}, {"track_id": 0, "bbox": [400.64306640625, 178.41073608398438, 408.9228515625, 188.33810424804688], "class_id": 1, "class_name": "ball", "team_id": -1}], "ball_owner": -1, "possession_team": -1, "spatial_info": {"field_position": [52.49999999999999, 23.68097645095256], "zone_id": 2, "zone_name": "def_right", "calibration_valid": true, "position_fallback": false}}, "5726": {"frame": 5726, "objects": [{"track_id": 7, "bbox": [353.5497131347656, 46.72566223144531, 372.0978698730469, 69.00970458984375], "class_id": 0, "class_name": "player", "team_id": -1}, {"track_id": 20, "bbox": [233.71115112304688, 155.228515625, 245.093994140625, 183.69012451171875], "class_id": 0, "class_name": "player", "team_id": -1}, {"track_id": 0, "bbox": [400.54522705078125, 178.56192016601562, 409.08367919921875, 188.88955688476562], "class_id": 1, "class_name": "ball", "team_id": -1}], "ball_owner": -1, "possession_team": -1, "spatial_info": {"field_position": [52.49999999999999, 23.691953260333147], "zone_id": 2, "zone_name": "def_right", "calibration_valid": true, "position_fallback": false}}, "5727": {"frame": 5727, "objects": [{"track_id": 20, "bbox": [233.90293884277344, 155.34228515625, 244.9912567138672, 183.55767822265625], "class_id": 0, "class_name": "player", "team_id": -1}, {"track_id": 7, "bbox": [353.69970703125, 46.889930725097656, 372.4891357421875, 69.21808624267578], "class_id": 0, "class_name": "player", "team_id": -1}, {"track_id": 0, "bbox": [400.5890197753906, 178.738525390625, 408.9735412597656, 189.08035278320312], "class_id": 1, "class_name": "ball", "team_id": -1}], "ball_owner": -1, "possession_team": -1, "spatial_info": {"field_position": [52.499999999999986, 23.695604160321164], "zone_id": 2, "zone_name": "def_right", "calibration_valid": true, "position_fallback": false}}, "5728": {"frame": 5728, "objects": [{"track_id": 20, "bbox": [233.54046630859375, 154.3886260986328, 245.0772705078125, 184.06077575683594], "class_id": 0, "class_name": "player", "team_id": -1}, {"track_id": 0, "bbox": [400.3975524902344, 178.79348754882812, 409.0022888183594, 189.38961791992188], "class_id": 1, "class_name": "ball", "team_id": -1}], "ball_owner": -1, "possession_team": -1, "spatial_info": {"field_position": [52.49999999999999, 23.701432460785618], "zone_id": 2, "zone_name": "def_right", "calibration_valid": true, "position_fallback": false}}, "5729": {"frame": 5729, "objects": [{"track_id": 20, "bbox": [233.20947265625, 153.01678466796875, 245.63128662109375, 184.234619140625], "class_id": 0, "class_name": "player", "team_id": -1}, {"track_id": 7, "bbox": [353.7410888671875, 46.57606887817383, 372.31488037109375, 70.21937561035156], "class_id": 0, "class_name": "player", "team_id": -1}, {"track_id": 0, "bbox": [400.2686767578125, 178.75225830078125, 409.2283935546875, 189.97259521484375], "class_id": 1, "class_name": "ball", "team_id": -1}], "ball_owner": -1, "possession_team": -1, "spatial_info": {"field_position": [52.499999999999986, 23.71308722370873], "zone_id": 2, "zone_name": "def_right", "calibration_valid": true, "position_fallback": false}}, "5730": {"frame": 5730, "objects": [{"track_id": 23, "bbox": [353.5059814453125, 46.52330780029297, 372.8671875, 71.68975067138672], "class_id": 0, "class_name": "player", "team_id": -1}, {"track_id": 2, "bbox": [233.20114135742188, 153.73306274414062, 245.47354125976562, 184.31430053710938], "class_id": 0, "class_name": "player", "team_id": -1}, {"track_id": 0, "bbox": [400.575439453125, 178.88677978515625, 409.39654541015625, 189.43621826171875], "class_id": 1, "class_name": "ball", "team_id": -1}], "ball_owner": -1, "possession_team": -1, "spatial_info": {"field_position": [52.499999999999986, 23.70329478134855], "zone_id": 2, "zone_name": "def_right", "calibration_valid": true, "position_fallback": false}}, "5731": {"frame": 5731, "objects": [{"track_id": 8, "bbox": [353.05059814453125, 46.14601135253906, 372.91412353515625, 72.39907836914062], "class_id": 0, "class_name": "player", "team_id": -1}, {"track_id": 0, "bbox": [400.282958984375, 178.75433349609375, 409.55224609375, 189.33734130859375], "class_id": 1, "class_name": "ball", "team_id": -1}], "ball_owner": -1, "possession_team": -1, "spatial_info": {"field_position": [52.499999999999986, 23.701120971442496], "zone_id": 2, "zone_name": "def_right", "calibration_valid": true, "position_fallback": false}}, "5732": {"frame": 5732, "objects": [{"track_id": 17, "bbox": [353.2293701171875, 46.2540283203125, 372.3861083984375, 72.34912109375], "class_id": 0, "class_name": "player", "team_id": -1}, {"track_id": 0, "bbox": [400.41192626953125, 178.63778686523438, 410.1903076171875, 189.43075561523438], "class_id": 1, "class_name": "ball", "team_id": -1}], "ball_owner": -1, "possession_team": -1, "spatial_info": {"field_position": [52.49999999999999, 23.704224429109072], "zone_id": 2, "zone_name": "def_right", "calibration_valid": true, "position_fallback": false}}, "5733": {"frame": 5733, "objects": [{"track_id": 10, "bbox": [353.57720947265625, 48.12848663330078, 371.9530029296875, 71.80419158935547], "class_id": 0, "class_name": "player", "team_id": -1}, {"track_id": 0, "bbox": [400.4794921875, 178.5849609375, 410.2420654296875, 189.14483642578125], "class_id": 1, "class_name": "ball", "team_id": -1}], "ball_owner": -1, "possession_team": -1, "spatial_info": {"field_position": [52.49999999999999, 23.69879442161293], "zone_id": 2, "zone_name": "def_right", "calibration_valid": true, "position_fallback": false}}, "5734": {"frame": 5734, "objects": [{"track_id": 10, "bbox": [353.56768798828125, 47.9940299987793, 371.90911865234375, 71.87678527832031], "class_id": 0, "class_name": "player", "team_id": -1}, {"track_id": 0, "bbox": [400.56890869140625, 178.37890625, 411.0322265625, 189.35595703125], "class_id": 1, "class_name": "ball", "team_id": -1}], "ball_owner": -1, "possession_team": -1, "spatial_info": {"field_position": [52.49999999999998, 23.7043943522311], "zone_id": 2, "zone_name": "def_right", "calibration_valid": true, "position_fallback": false}}, "5735": {"frame": 5735, "objects": [{"track_id": 13, "bbox": [353.3229064941406, 48.263450622558594, 372.3628234863281, 72.20970916748047], "class_id": 0, "class_name": "player", "team_id": -1}, {"track_id": 0, "bbox": [15.906371116638184, 164.9442138671875, 32.9327392578125, 177.0069580078125], "class_id": 1, "class_name": "ball", "team_id": -1}], "ball_owner": -1, "possession_team": -1, "spatial_info": {"field_position": [52.5, 30.051570084209406], "zone_id": 2, "zone_name": "def_right", "calibration_valid": true, "position_fallback": false}}, "5736": {"frame": 5736, "objects": [{"track_id": 13, "bbox": [353.0187683105469, 49.067291259765625, 372.3401184082031, 72.17156982421875], "class_id": 0, "class_name": "player", "team_id": -1}, {"track_id": 0, "bbox": [16.106525421142578, 164.937744140625, 32.58772659301758, 176.75390625], "class_id": 1, "class_name": "ball", "team_id": -1}], "ball_owner": -1, "possession_team": -1, "spatial_info": {"field_position": [52.5, 30.067238233523803], "zone_id": 2, "zone_name": "def_right", "calibration_valid": true, "position_fallback": false}}, "5737": {"frame": 5737, "objects": [{"track_id": 13, "bbox": [353.28143310546875, 49.359798431396484, 372.43511962890625, 72.29727172851562], "class_id": 0, "class_name": "player", "team_id": -1}, {"track_id": 0, "bbox": [16.394420623779297, 165.63543701171875, 32.799983978271484, 176.46600341796875], "class_id": 1, "class_name": "ball", "team_id": -1}], "ball_owner": -1, "possession_team": -1, "spatial_info": {"field_position": [52.5, 30.109631580666132], "zone_id": 2, "zone_name": "def_right", "calibration_valid": true, "position_fallback": false}}, "5738": {"frame": 5738, "objects": [{"track_id": 13, "bbox": [353.1436767578125, 49.1923942565918, 372.916259765625, 72.79066467285156], "class_id": 0, "class_name": "player", "team_id": -1}, {"track_id": 0, "bbox": [16.29644012451172, 165.22213745117188, 33.53917694091797, 176.80743408203125], "class_id": 1, "class_name": "ball", "team_id": -1}], "ball_owner": -1, "possession_team": -1, "spatial_info": {"field_position": [52.49999999999999, 30.105048514801627], "zone_id": 2, "zone_name": "def_right", "calibration_valid": true, "position_fallback": false}}, "5739": {"frame": 5739, "objects": [{"track_id": 13, "bbox": [353.1671142578125, 49.07887268066406, 373.00958251953125, 73.03654479980469], "class_id": 0, "class_name": "player", "team_id": -1}, {"track_id": 0, "bbox": [16.94156265258789, 165.20123291015625, 33.02248764038086, 176.7723388671875], "class_id": 1, "class_name": "ball", "team_id": -1}], "ball_owner": -1, "possession_team": -1, "spatial_info": {"field_position": [52.5, 30.112778982789834], "zone_id": 2, "zone_name": "def_right", "calibration_valid": true, "position_fallback": false}}, "5740": {"frame": 5740, "objects": [{"track_id": 13, "bbox": [353.22503662109375, 49.134979248046875, 372.93536376953125, 73.1397705078125], "class_id": 0, "class_name": "player", "team_id": -1}, {"track_id": 0, "bbox": [17.720497131347656, 165.013916015625, 33.536888122558594, 176.96112060546875], "class_id": 1, "class_name": "ball", "team_id": -1}], "ball_owner": -1, "possession_team": -1, "spatial_info": {"field_position": [52.5, 30.14565120346923], "zone_id": 2, "zone_name": "def_right", "calibration_valid": true, "position_fallback": false}}, "5741": {"frame": 5741, "objects": [{"track_id": 13, "bbox": [353.3502502441406, 49.31645965576172, 373.2757873535156, 73.4765396118164], "class_id": 0, "class_name": "player", "team_id": -1}, {"track_id": 0, "bbox": [19.206806182861328, 165.29171752929688, 33.119850158691406, 176.35409545898438], "class_id": 1, "class_name": "ball", "team_id": -1}], "ball_owner": -1, "possession_team": -1, "spatial_info": {"field_position": [52.50000000000001, 30.238149437127845], "zone_id": -1, "zone_name": "unknown", "calibration_valid": true, "position_fallback": false}}, "5742": {"frame": 5742, "objects": [{"track_id": 13, "bbox": [353.128173828125, 49.886627197265625, 373.1959228515625, 73.99470520019531], "class_id": 0, "class_name": "player", "team_id": -1}, {"track_id": 0, "bbox": [21.200847625732422, 165.73313903808594, 33.15286636352539, 175.7869415283203], "class_id": 1, "class_name": "ball", "team_id": -1}], "ball_owner": -1, "possession_team": -1, "spatial_info": {"field_position": [52.5, 30.367043593197316], "zone_id": 2, "zone_name": "def_right", "calibration_valid": true, "position_fallback": false}}, "5743": {"frame": 5743, "objects": [{"track_id": 13, "bbox": [352.77703857421875, 49.74494934082031, 373.24676513671875, 74.78781127929688], "class_id": 0, "class_name": "player", "team_id": -1}, {"track_id": 0, "bbox": [21.564720153808594, 165.71034240722656, 33.830955505371094, 175.77696228027344], "class_id": 1, "class_name": "ball", "team_id": -1}], "ball_owner": -1, "possession_team": -1, "spatial_info": {"field_position": [52.49999999999999, 30.410302860515962], "zone_id": 2, "zone_name": "def_right", "calibration_valid": true, "position_fallback": false}}, "5744": {"frame": 5744, "objects": [{"track_id": 12, "bbox": [352.959228515625, 49.97776794433594, 373.5064697265625, 75.00787353515625], "class_id": 0, "class_name": "player", "team_id": -1}, {"track_id": 0, "bbox": [21.520061492919922, 165.04710388183594, 34.6722297668457, 175.9181671142578], "class_id": 1, "class_name": "ball", "team_id": -1}], "ball_owner": -1, "possession_team": -1, "spatial_info": {"field_position": [52.49999999999999, 30.430814072838775], "zone_id": 2, "zone_name": "def_right", "calibration_valid": true, "position_fallback": false}}, "5745": {"frame": 5745, "objects": [{"track_id": 16, "bbox": [351.7783203125, 50.068695068359375, 374.2913818359375, 76.72531127929688], "class_id": 0, "class_name": "player", "team_id": -1}, {"track_id": 3, "bbox": [401.4027099609375, 178.82376098632812, 417.19952392578125, 199.09402465820312], "class_id": 0, "class_name": "player", "team_id": -1}, {"track_id": 0, "bbox": [21.409820556640625, 165.0496368408203, 34.98877716064453, 176.16017150878906], "class_id": 1, "class_name": "ball", "team_id": -1}], "ball_owner": -1, "possession_team": -1, "spatial_info": {"field_position": [52.5, 30.418190278900177], "zone_id": 2, "zone_name": "def_right", "calibration_valid": true, "position_fallback": false}}, "5746": {"frame": 5746, "objects": [{"track_id": 15, "bbox": [352.05523681640625, 50.82771301269531, 374.05731201171875, 76.60455322265625], "class_id": 0, "class_name": "player", "team_id": -1}, {"track_id": 0, "bbox": [21.748584747314453, 165.148193359375, 34.6899299621582, 175.8560791015625], "class_id": 1, "class_name": "ball", "team_id": -1}], "ball_owner": -1, "possession_team": -1, "spatial_info": {"field_position": [52.5, 30.446455366375773], "zone_id": 2, "zone_name": "def_right", "calibration_valid": true, "position_fallback": false}}, "5747": {"frame": 5747, "objects": [{"track_id": 22, "bbox": [352.1168518066406, 50.66419982910156, 374.0052185058594, 76.88615417480469], "class_id": 0, "class_name": "player", "team_id": -1}, {"track_id": 19, "bbox": [401.9001770019531, 178.79725646972656, 416.4895324707031, 198.6259002685547], "class_id": 0, "class_name": "player", "team_id": -1}, {"track_id": 0, "bbox": [21.726097106933594, 165.09637451171875, 34.633384704589844, 176.1280517578125], "class_id": 1, "class_name": "ball", "team_id": -1}], "ball_owner": -1, "possession_team": -1, "spatial_info": {"field_position": [52.50000000000001, 30.419382708493885], "zone_id": -1, "zone_name": "unknown", "calibration_valid": true, "position_fallback": false}}, "5748": {"frame": 5748, "objects": [{"track_id": 18, "bbox": [402.196044921875, 178.49447631835938, 416.4368896484375, 198.36526489257812], "class_id": 0, "class_name": "player", "team_id": -1}, {"track_id": 4, "bbox": [352.4605712890625, 50.94419479370117, 373.9793701171875, 76.84675598144531], "class_id": 0, "class_name": "player", "team_id": -1}, {"track_id": 0, "bbox": [21.980789184570312, 165.28152465820312, 34.61763000488281, 176.104248046875], "class_id": 1, "class_name": "ball", "team_id": -1}], "ball_owner": -1, "possession_team": -1, "spatial_info": {"field_position": [52.5, 30.43136571321435], "zone_id": 2, "zone_name": "def_right", "calibration_valid": true, "position_fallback": false}}, "5749": {"frame": 5749, "objects": [{"track_id": 11, "bbox": [402.28729248046875, 178.55577087402344, 416.58843994140625, 198.13804626464844], "class_id": 0, "class_name": "player", "team_id": 1}, {"track_id": 0, "bbox": [22.346942901611328, 165.45843505859375, 33.75654983520508, 175.83599853515625], "class_id": 1, "class_name": "ball", "team_id": -1}], "ball_owner": -1, "possession_team": -1, "spatial_info": {"field_position": [52.50000000000001, 30.434315568310986], "zone_id": -1, "zone_name": "unknown", "calibration_valid": true, "position_fallback": false}}, "5750": {"frame": 5750, "objects": [{"track_id": 13, "bbox": [354.45782470703125, 52.80078125, 373.28729248046875, 74.49577331542969], "class_id": 0, "class_name": "player", "team_id": -1}, {"track_id": 11, "bbox": [402.7457275390625, 178.47286987304688, 416.8427734375, 197.94863891601562], "class_id": 0, "class_name": "player", "team_id": 1}, {"track_id": 0, "bbox": [382.0351257324219, 228.61764526367188, 390.5224304199219, 236.84146118164062], "class_id": 1, "class_name": "ball", "team_id": -1}], "ball_owner": 11, "possession_team": 1, "spatial_info": {"field_position": [52.499999999999986, 24.631204202317413], "zone_id": 2, "zone_name": "def_right", "calibration_valid": true, "position_fallback": false}}, "5751": {"frame": 5751, "objects": [{"track_id": 13, "bbox": [353.84307861328125, 52.395050048828125, 373.52288818359375, 75.99617004394531], "class_id": 0, "class_name": "player", "team_id": -1}, {"track_id": 11, "bbox": [403.23675537109375, 178.64987182617188, 417.42547607421875, 197.95901489257812], "class_id": 0, "class_name": "player", "team_id": 1}, {"track_id": 0, "bbox": [23.780345916748047, 166.31863403320312, 35.760963439941406, 176.44631958007812], "class_id": 1, "class_name": "ball", "team_id": -1}], "ball_owner": -1, "possession_team": -1, "spatial_info": {"field_position": [52.50000000000001, 30.525565993968225], "zone_id": -1, "zone_name": "unknown", "calibration_valid": true, "position_fallback": false}}, "5752": {"frame": 5752, "objects": [{"track_id": 6, "bbox": [352.936279296875, 52.07756042480469, 374.0872802734375, 77.76600646972656], "class_id": 0, "class_name": "player", "team_id": -1}, {"track_id": 1, "bbox": [403.36358642578125, 178.78982543945312, 417.40277099609375, 197.83529663085938], "class_id": 0, "class_name": "player", "team_id": -1}, {"track_id": 0, "bbox": [24.560413360595703, 166.05819702148438, 39.3151741027832, 177.0640869140625], "class_id": 1, "class_name": "ball", "team_id": -1}], "ball_owner": -1, "possession_team": -1, "spatial_info": {"field_position": [52.50000000000001, 30.66151664108165], "zone_id": -1, "zone_name": "unknown", "calibration_valid": true, "position_fallback": false}}, "5753": {"frame": 5753, "objects": [{"track_id": 21, "bbox": [352.844482421875, 51.61933898925781, 374.6912841796875, 78.55235290527344], "class_id": 0, "class_name": "player", "team_id": -1}, {"track_id": 9, "bbox": [403.91485595703125, 179.64141845703125, 417.80450439453125, 197.79290771484375], "class_id": 0, "class_name": "player", "team_id": 0}, {"track_id": 0, "bbox": [24.73798179626465, 166.13552856445312, 41.206077575683594, 177.04916381835938], "class_id": 1, "class_name": "ball", "team_id": -1}], "ball_owner": -1, "possession_team": -1, "spatial_info": {"field_position": [52.5, 30.75875211214241], "zone_id": 2, "zone_name": "def_right", "calibration_valid": true, "position_fallback": false}}, "5754": {"frame": 5754, "objects": [{"track_id": 5, "bbox": [352.9947509765625, 51.97346496582031, 374.6546630859375, 79.08071899414062], "class_id": 0, "class_name": "player", "team_id": -1}, {"track_id": 0, "bbox": [25.274049758911133, 165.98080444335938, 41.6566162109375, 177.75338745117188], "class_id": 1, "class_name": "ball", "team_id": -1}], "ball_owner": -1, "possession_team": -1, "spatial_info": {"field_position": [52.50000000000001, 30.738869534605563], "zone_id": -1, "zone_name": "unknown", "calibration_valid": true, "position_fallback": false}}, "5755": {"frame": 5755, "objects": [{"track_id": 14, "bbox": [353.32769775390625, 52.11772155761719, 375.00018310546875, 78.9200439453125], "class_id": 0, "class_name": "player", "team_id": -1}, {"track_id": 0, "bbox": [405.2285461425781, 180.0734100341797, 415.2856750488281, 192.08714294433594], "class_id": 1, "class_name": "ball", "team_id": -1}], "ball_owner": -1, "possession_team": -1, "spatial_info": {"field_position": [52.49999999999999, 23.771713482866748], "zone_id": 2, "zone_name": "def_right", "calibration_valid": true, "position_fallback": false}}, "5756": {"frame": 5756, "objects": [{"track_id": 5, "bbox": [352.94287109375, 52.09580993652344, 374.950927734375, 79.53880310058594], "class_id": 0, "class_name": "player", "team_id": -1}, {"track_id": 0, "bbox": [405.4412536621094, 179.93212890625, 416.2138977050781, 193.62216186523438], "class_id": 1, "class_name": "ball", "team_id": -1}], "ball_owner": -1, "possession_team": -1, "spatial_info": {"field_position": [52.49999999999998, 23.803108346878336], "zone_id": 2, "zone_name": "def_right", "calibration_valid": true, "position_fallback": false}}, "5757": {"frame": 5757, "objects": [{"track_id": 14, "bbox": [353.33367919921875, 52.24128723144531, 374.76922607421875, 78.78816223144531], "class_id": 0, "class_name": "player", "team_id": -1}, {"track_id": 2, "bbox": [225.038818359375, 142.16531372070312, 238.75506591796875, 169.84005737304688], "class_id": 0, "class_name": "player", "team_id": -1}, {"track_id": 0, "bbox": [386.1227111816406, 224.54763793945312, 397.0592346191406, 235.59628295898438], "class_id": 1, "class_name": "ball", "team_id": -1}], "ball_owner": -1, "possession_team": -1, "spatial_info": {"field_position": [52.49999999999999, 24.607160903920118], "zone_id": 2, "zone_name": "def_right", "calibration_valid": true, "position_fallback": false}}, "5758": {"frame": 5758, "objects": [{"track_id": 14, "bbox": [353.68975830078125, 53.38252258300781, 374.895263671875, 78.87913513183594], "class_id": 0, "class_name": "player", "team_id": -1}, {"track_id": 2, "bbox": [224.56634521484375, 141.61378479003906, 239.46221923828125, 172.65843200683594], "class_id": 0, "class_name": "player", "team_id": -1}, {"track_id": 0, "bbox": [387.77789306640625, 224.98802185058594, 397.41082763671875, 234.8852996826172], "class_id": 1, "class_name": "ball", "team_id": -1}], "ball_owner": -1, "possession_team": -1, "spatial_info": {"field_position": [52.49999999999999, 24.592965610333426], "zone_id": 2, "zone_name": "def_right", "calibration_valid": true, "position_fallback": false}}, "5759": {"frame": 5759, "objects": [{"track_id": 7, "bbox": [353.543701171875, 53.09501647949219, 375.36474609375, 79.42884826660156], "class_id": 0, "class_name": "player", "team_id": -1}, {"track_id": 20, "bbox": [224.4794921875, 141.66836547851562, 239.79736328125, 180.51028442382812], "class_id": 0, "class_name": "player", "team_id": -1}, {"track_id": 0, "bbox": [389.3027648925781, 225.33653259277344, 398.0054016113281, 234.3512420654297], "class_id": 1, "class_name": "ball", "team_id": -1}], "ball_owner": -1, "possession_team": -1, "spatial_info": {"field_position": [52.499999999999986, 24.582505357670133], "zone_id": 2, "zone_name": "def_right", "calibration_valid": true, "position_fallback": false}}, "5760": {"frame": 5760, "objects": [{"track_id": 7, "bbox": [353.46246337890625, 53.35487365722656, 375.63214111328125, 80.31132507324219], "class_id": 0, "class_name": "player", "team_id": -1}, {"track_id": 0, "bbox": [389.6566467285156, 224.6171112060547, 398.7267150878906, 234.48548889160156], "class_id": 1, "class_name": "ball", "team_id": -1}], "ball_owner": -1, "possession_team": -1, "spatial_info": {"field_position": [52.499999999999986, 24.585486517720277], "zone_id": 2, "zone_name": "def_right", "calibration_valid": true, "position_fallback": false}}, "5761": {"frame": 5761, "objects": [{"track_id": 7, "bbox": [353.7459716796875, 53.72564697265625, 375.32684326171875, 79.95318603515625], "class_id": 0, "class_name": "player", "team_id": -1}, {"track_id": 2, "bbox": [224.635498046875, 141.76385498046875, 239.66448974609375, 177.30197143554688], "class_id": 0, "class_name": "player", "team_id": -1}, {"track_id": 0, "bbox": [389.59429931640625, 223.4378662109375, 399.27044677734375, 234.336181640625], "class_id": 1, "class_name": "ball", "team_id": -1}], "ball_owner": -1, "possession_team": -1, "spatial_info": {"field_position": [52.499999999999986, 24.582552488024703], "zone_id": 2, "zone_name": "def_right", "calibration_valid": true, "position_fallback": false}}, "5762": {"frame": 5762, "objects": [{"track_id": 23, "bbox": [354.12420654296875, 53.158721923828125, 375.63507080078125, 80.67745971679688], "class_id": 0, "class_name": "player", "team_id": -1}, {"track_id": 17, "bbox": [405.30548095703125, 180.3394775390625, 420.41766357421875, 197.18072509765625], "class_id": 0, "class_name": "player", "team_id": -1}, {"track_id": 0, "bbox": [29.624134063720703, 163.80291748046875, 49.649471282958984, 177.96087646484375], "class_id": 1, "class_name": "ball", "team_id": -1}], "ball_owner": -1, "possession_team": -1, "spatial_info": {"field_position": [52.5, 31.363622884682545], "zone_id": 2, "zone_name": "def_right", "calibration_valid": true, "position_fallback": false}}, "5763": {"frame": 5763, "objects": [{"track_id": 8, "bbox": [225.0151824951172, 142.40652465820312, 238.37974548339844, 169.7034912109375], "class_id": 0, "class_name": "player", "team_id": -1}, {"track_id": 0, "bbox": [29.496625900268555, 163.68063354492188, 49.057342529296875, 178.45877075195312], "class_id": 1, "class_name": "ball", "team_id": -1}], "ball_owner": -1, "possession_team": -1, "spatial_info": {"field_position": [52.5, 31.270400769985244], "zone_id": 2, "zone_name": "def_right", "calibration_valid": true, "position_fallback": false}}, "5764": {"frame": 5764, "objects": [{"track_id": 10, "bbox": [224.65206909179688, 142.552001953125, 238.24368286132812, 169.78634643554688], "class_id": 0, "class_name": "player", "team_id": -1}, {"track_id": 0, "bbox": [30.54944610595703, 164.72084045410156, 47.941261291503906, 177.0563507080078], "class_id": 1, "class_name": "ball", "team_id": -1}], "ball_owner": -1, "possession_team": -1, "spatial_info": {"field_position": [52.5, 31.412845210524313], "zone_id": 2, "zone_name": "def_right", "calibration_valid": true, "position_fallback": false}}, "5765": {"frame": 5765, "objects": [{"track_id": 10, "bbox": [224.56922912597656, 143.2452392578125, 238.1709442138672, 170.640869140625], "class_id": 0, "class_name": "player", "team_id": -1}, {"track_id": 17, "bbox": [405.622802734375, 179.6177978515625, 420.9803466796875, 197.5230712890625], "class_id": 0, "class_name": "player", "team_id": -1}, {"track_id": 7, "bbox": [354.86663818359375, 54.983612060546875, 375.58880615234375, 81.72677612304688], "class_id": 0, "class_name": "player", "team_id": -1}, {"track_id": 9, "bbox": [407.9490966796875, 152.96127319335938, 423.3524169921875, 174.57608032226562], "class_id": 0, "class_name": "player", "team_id": 0}, {"track_id": 0, "bbox": [29.777610778808594, 162.97579956054688, 48.810462951660156, 178.65615844726562], "class_id": 1, "class_name": "ball", "team_id": -1}], "ball_owner": -1, "possession_team": -1, "spatial_info": {"field_position": [52.50000000000001, 31.25176015431478], "zone_id": -1, "zone_name": "unknown", "calibration_valid": true, "position_fallback": false}}, "5766": {"frame": 5766, "objects": [{"track_id": 10, "bbox": [224.43511962890625, 143.69229125976562, 238.31362915039062, 176.52761840820312], "class_id": 0, "class_name": "player", "team_id": -1}, {"track_id": 17, "bbox": [405.8846435546875, 179.5977783203125, 421.2095947265625, 197.46209716796875], "class_id": 0, "class_name": "player", "team_id": -1}, {"track_id": 9, "bbox": [409.1485595703125, 153.03643798828125, 422.90936279296875, 173.744873046875], "class_id": 0, "class_name": "player", "team_id": 0}, {"track_id": 7, "bbox": [356.10223388671875, 55.839569091796875, 374.60174560546875, 81.44656372070312], "class_id": 0, "class_name": "player", "team_id": -1}, {"track_id": 19, "bbox": [260.09271240234375, 66.8612060546875, 274.35809326171875, 85.44754028320312], "class_id": 0, "class_name": "player", "team_id": -1}, {"track_id": 0, "bbox": [30.602378845214844, 164.04635620117188, 48.23197937011719, 177.48941040039062], "class_id": 1, "class_name": "ball", "team_id": -1}], "ball_owner": -1, "possession_team": -1, "spatial_info": {"field_position": [52.50000000000001, 31.387560939342634], "zone_id": -1, "zone_name": "unknown", "calibration_valid": true, "position_fallback": false}}, "5767": {"frame": 5767, "objects": [{"track_id": 8, "bbox": [224.696533203125, 144.028564453125, 237.77359008789062, 169.36370849609375], "class_id": 0, "class_name": "player", "team_id": -1}, {"track_id": 9, "bbox": [408.22308349609375, 152.09078979492188, 424.00616455078125, 174.22952270507812], "class_id": 0, "class_name": "player", "team_id": 0}, {"track_id": 17, "bbox": [405.8101806640625, 179.01016235351562, 421.71917724609375, 197.64450073242188], "class_id": 0, "class_name": "player", "team_id": -1}, {"track_id": 7, "bbox": [356.58538818359375, 56.684783935546875, 374.11224365234375, 80.87588500976562], "class_id": 0, "class_name": "player", "team_id": -1}, {"track_id": 0, "bbox": [30.722023010253906, 163.94589233398438, 49.97865295410156, 177.64230346679688], "class_id": 1, "class_name": "ball", "team_id": -1}], "ball_owner": -1, "possession_team": -1, "spatial_info": {"field_position": [52.5, 31.480978822484843], "zone_id": 2, "zone_name": "def_right", "calibration_valid": true, "position_fallback": false}}, "5768": {"frame": 5768, "objects": [{"track_id": 17, "bbox": [405.84747314453125, 178.99853515625, 421.99517822265625, 197.94451904296875], "class_id": 0, "class_name": "player", "team_id": -1}, {"track_id": 8, "bbox": [224.63072204589844, 144.61093139648438, 237.5731658935547, 169.40606689453125], "class_id": 0, "class_name": "player", "team_id": -1}, {"track_id": 9, "bbox": [408.3003845214844, 151.9609375, 424.0948791503906, 174.08831787109375], "class_id": 0, "class_name": "player", "team_id": 0}, {"track_id": 7, "bbox": [356.6534118652344, 56.43798065185547, 374.4375305175781, 80.96634674072266], "class_id": 0, "class_name": "player", "team_id": -1}, {"track_id": 0, "bbox": [396.88153076171875, 221.0167999267578, 405.55194091796875, 229.5313262939453], "class_id": 1, "class_name": "ball", "team_id": -1}], "ball_owner": 17, "possession_team": -1, "spatial_info": {"field_position": [52.499999999999986, 24.489876111003376], "zone_id": 2, "zone_name": "def_right", "calibration_valid": true, "position_fallback": false}}, "5769": {"frame": 5769, "objects": [{"track_id": 8, "bbox": [224.35340881347656, 144.90277099609375, 237.72312927246094, 169.38470458984375], "class_id": 0, "class_name": "player", "team_id": -1}, {"track_id": 17, "bbox": [405.74456787109375, 178.95941162109375, 422.71575927734375, 197.8221435546875], "class_id": 0, "class_name": "player", "team_id": -1}, {"track_id": 9, "bbox": [408.33123779296875, 150.80264282226562, 424.25457763671875, 173.98880004882812], "class_id": 0, "class_name": "player", "team_id": 0}, {"track_id": 7, "bbox": [356.69866943359375, 56.65446472167969, 374.41412353515625, 81.05296325683594], "class_id": 0, "class_name": "player", "team_id": -1}, {"track_id": 0, "bbox": [397.33843994140625, 219.9776611328125, 406.03240966796875, 229.01263427734375], "class_id": 1, "class_name": "ball", "team_id": -1}], "ball_owner": 17, "possession_team": -1, "spatial_info": {"field_position": [52.49999999999999, 24.479911449187007], "zone_id": 2, "zone_name": "def_right", "calibration_valid": true, "position_fallback": false}}, "5770": {"frame": 5770, "objects": [{"track_id": 17, "bbox": [405.3494873046875, 178.3990936279297, 422.8118896484375, 199.3316192626953], "class_id": 0, "class_name": "player", "team_id": -1}, {"track_id": 8, "bbox": [224.42697143554688, 145.4952850341797, 237.66470336914062, 169.01637268066406], "class_id": 0, "class_name": "player", "team_id": -1}, {"track_id": 9, "bbox": [408.31951904296875, 149.7128448486328, 424.52178955078125, 173.87486267089844], "class_id": 0, "class_name": "player", "team_id": 0}, {"track_id": 7, "bbox": [356.8665771484375, 56.88963317871094, 374.56585693359375, 81.25906372070312], "class_id": 0, "class_name": "player", "team_id": -1}, {"track_id": 0, "bbox": [412.9901123046875, 139.7160186767578, 421.2327880859375, 148.47520446777344], "class_id": 1, "class_name": "ball", "team_id": -1}], "ball_owner": 9, "possession_team": 0, "spatial_info": {"field_position": [52.499999999999986, 22.964806822388763], "zone_id": 2, "zone_name": "def_right", "calibration_valid": true, "position_fallback": false}}, "5771": {"frame": 5771, "objects": [{"track_id": 3, "bbox": [405.057861328125, 178.03707885742188, 423.3519287109375, 199.32565307617188], "class_id": 0, "class_name": "player", "team_id": -1}, {"track_id": 12, "bbox": [224.01351928710938, 145.55560302734375, 237.79824829101562, 171.8582763671875], "class_id": 0, "class_name": "player", "team_id": -1}, {"track_id": 0, "bbox": [35.25165939331055, 164.5072784423828, 55.88693618774414, 177.0656280517578], "class_id": 1, "class_name": "ball", "team_id": -1}], "ball_owner": -1, "possession_team": -1, "spatial_info": {"field_position": [52.50000000000001, 32.233118320554105], "zone_id": -1, "zone_name": "unknown", "calibration_valid": true, "position_fallback": false}}, "5772": {"frame": 5772, "objects": [{"track_id": 16, "bbox": [405.56170654296875, 177.4691162109375, 423.73040771484375, 199.38043212890625], "class_id": 0, "class_name": "player", "team_id": -1}, {"track_id": 15, "bbox": [223.29818725585938, 145.0568084716797, 238.02438354492188, 179.6339874267578], "class_id": 0, "class_name": "player", "team_id": -1}, {"track_id": 0, "bbox": [36.635589599609375, 164.91220092773438, 55.43916320800781, 176.52444458007812], "class_id": 1, "class_name": "ball", "team_id": -1}], "ball_owner": -1, "possession_team": -1, "spatial_info": {"field_position": [52.50000000000001, 32.36576705361972], "zone_id": -1, "zone_name": "unknown", "calibration_valid": true, "position_fallback": false}}, "5773": {"frame": 5773, "objects": [{"track_id": 18, "bbox": [405.9044189453125, 177.7398681640625, 423.4453125, 199.22537231445312], "class_id": 0, "class_name": "player", "team_id": -1}, {"track_id": 22, "bbox": [408.80596923828125, 151.56234741210938, 425.159912109375, 174.08358764648438], "class_id": 0, "class_name": "player", "team_id": -1}, {"track_id": 0, "bbox": [37.71234893798828, 164.92251586914062, 53.92778778076172, 176.37765502929688], "class_id": 1, "class_name": "ball", "team_id": -1}], "ball_owner": -1, "possession_team": -1, "spatial_info": {"field_position": [52.50000000000001, 32.35059564379595], "zone_id": -1, "zone_name": "unknown", "calibration_valid": true, "position_fallback": false}}, "5774": {"frame": 5774, "objects": [{"track_id": 4, "bbox": [405.8612060546875, 177.70053100585938, 423.6077880859375, 199.33859252929688], "class_id": 0, "class_name": "player", "team_id": -1}, {"track_id": 0, "bbox": [38.10401153564453, 165.41151428222656, 53.14972686767578, 176.2845001220703], "class_id": 1, "class_name": "ball", "team_id": -1}], "ball_owner": -1, "possession_team": -1, "spatial_info": {"field_position": [52.50000000000001, 32.33284890124947], "zone_id": -1, "zone_name": "unknown", "calibration_valid": true, "position_fallback": false}}}